nchain/__init__.py
nchain/app.py
nchain/bots/base_bot.py
nchain/bots/bot_plugin_manager.py
nchain/bots/telegram_bot.py
nchain/chunkers/__init__.py
nchain/chunkers/base_chunker.py
nchain/chunkers/sqlite_chunker.py
nchain/chunkers/text_chunker.py
nchain/cli.py
nchain/config/__init__.py
nchain/config/config_module.py
nchain/config/docker/Dockerfile
nchain/config/docker/docker-compose.yaml
nchain/config/settings.py
nchain/embedders/__init__.py
nchain/embedders/base_embedder.py
nchain/embedders/huggingface_embedder.py
nchain/embedders/sentence_transformers_embedder.py
nchain/loaders/__init__.py
nchain/loaders/arxiv_loader.py
nchain/loaders/base_loader.py
nchain/loaders/pdf_loader.py
nchain/loaders/sitemap_loader.py
nchain/loaders/sqlite_loader.py
nchain/loaders/text_loader.py
nchain/models/core.py
nchain/models/dynamic_model_generator.py
nchain/models/generic_model.py
nchain/pipeline/__init__.py
nchain/pipeline/data_pipeline.py
nchain/utils/__init__.py
nchain/utils/detection.py
nchain/utils/helpers.py
nchain/utils/sqlite_logger.py
nchain/vectordb/__init__.py
nchain/vectordb/base_vectordb.py
nchain/vectordb/faiss_vectordb.py
nchain/vectordb/sqlite_vectordb.py
nchain-0.13.post4.dist-info/METADATA
nchain-0.13.post4.dist-info/WHEEL
nchain-0.13.post4.dist-info/entry_points.txt
nchain-0.13.post4.dist-info/RECORD
