Metadata-Version: 2.1
Name: nChain
Version: 0.13.post4
Summary: nchain is a flexible and efficent framework to create LLM bots using embeddings over extensible dataset
License: Apache License
Author: James Liu
Author-email: james@bayjarvis.com
Requires-Python: >=3.10,<3.13
Classifier: License :: Other/Proprietary License
Classifier: Programming Language :: Python :: 3
Classifier: Programming Language :: Python :: 3.10
Classifier: Programming Language :: Python :: 3.11
Provides-Extra: opensource
Provides-Extra: test
Requires-Dist: annoy (>=1.17.3,<2.0.0)
Requires-Dist: arxiv (>=1.4.8,<2.0.0)
Requires-Dist: beautifulsoup4 (>=4.12.2,<5.0.0)
Requires-Dist: click (>=8.1.7,<9.0.0)
Requires-Dist: faiss-cpu (>=1.7.1,<2.0.0)
Requires-Dist: lxml (>=4.9.2,<5.0.0)
Requires-Dist: nltk (>=3.5)
Requires-Dist: numpy (>=1.26.0,<2.0.0)
Requires-Dist: openai (>=0.27.5,<0.28.0)
Requires-Dist: pydantic (>=2.4.2,<3.0.0)
Requires-Dist: pypdf (>=3.11.0,<4.0.0)
Requires-Dist: python-dotenv (>=1.0.0,<2.0.0)
Requires-Dist: requests (>=2.31.0,<3.0.0)
Requires-Dist: sentence-transformers (>=2.2.2,<3.0.0) ; extra == "opensource"
Requires-Dist: sqlite-utils (>=3.35.1,<4.0.0)
